{
  "notes": [
    {
      "title": "Tanvir's Birthday",
      "details": "hhdklflsdaklhhdklflsdaklhhdklflsdaklhhdklflsdaklhhdklflsdaklhhdklflsdakl  hhdklflsdaklhhdklflsdakl",
      "category": "reminders",
      "id": 1
    },
    {
      "title": "Tanvir's Birthday",
      "details": "hhdklflsdakl",
      "category": "reminders",
      "id": 3
    },
    {
      "title": "Another Birhday",
      "details": "Lorem Ipsum has been the industry's standard dummy text ever since the 1500s, when an unknown pr",
      "category": "todo",
      "id": 6
    },
    {
      "title": "Roger Birthday",
      "details": "industry. Lorem Ipsum has been the industry's standard dummy text ever since the 1500s, when an unknown prindustry. Lorem Ipsum has been the industry's standard dummy text ever since the 1500s, when an unknown pr",
      "category": "work",
      "id": 7
    },
    {
      "title": "New note",
      "details": "hello Tanvir",
      "category": "work",
      "id": 8
    },
    {
      "title": "New Tanvir",
      "details": "hshshsajhasd",
      "category": "money",
      "id": 9
    },
    {
      "title": "as",
      "details": "a",
      "category": "todo",
      "id": 10
    }
  ]
}